gse_gsatmicro_utils/__init__.py
gse_gsatmicro_utils/constants.py
gse_gsatmicro_utils/detect_ports.py
gse_gsatmicro_utils/detect_ports_linux.py
gse_gsatmicro_utils/detect_ports_osx.py
gse_gsatmicro_utils/detect_ports_windows.py
gse_gsatmicro_utils/ser_driver.py
gse_gsatmicro_utils/utils.py
gse_gsatmicro_utils-3.1.0.dist-info/METADATA
gse_gsatmicro_utils-3.1.0.dist-info/WHEEL
gse_gsatmicro_utils-3.1.0.dist-info/licenses/LICENSE.md
gse_gsatmicro_utils-3.1.0.dist-info/RECORD
