Metadata-Version: 2.4
Name: gse-gsatmicro-utils
Version: 3.1.0
Summary: GSE utility functions
Project-URL: homepage, https://www.gsat.us
Author-email: Bogdan Marinescu <bogdan@gsat.us>
License-File: LICENSE.md
Requires-Python: >=3.10
Requires-Dist: colorama>=0.4.6
Requires-Dist: pyserial>=3.5
Requires-Dist: pyyaml>=6.0.2
